odoo/addons/fieldservice_timeline/README.rst
odoo/addons/fieldservice_timeline/__init__.py
odoo/addons/fieldservice_timeline/__manifest__.py
odoo/addons/fieldservice_timeline/hooks.py
odoo/addons/fieldservice_timeline/i18n/es.po
odoo/addons/fieldservice_timeline/i18n/es_AR.po
odoo/addons/fieldservice_timeline/i18n/fieldservice_timeline.pot
odoo/addons/fieldservice_timeline/i18n/it.po
odoo/addons/fieldservice_timeline/i18n/pt_BR.po
odoo/addons/fieldservice_timeline/readme/CONFIGURE.rst
odoo/addons/fieldservice_timeline/readme/CONTRIBUTORS.rst
odoo/addons/fieldservice_timeline/readme/CREDITS.rst
odoo/addons/fieldservice_timeline/readme/DESCRIPTION.rst
odoo/addons/fieldservice_timeline/readme/ROADMAP.rst
odoo/addons/fieldservice_timeline/static/description/icon.png
odoo/addons/fieldservice_timeline/static/description/index.html
odoo/addons/fieldservice_timeline/static/src/js/custom_fillter.js
odoo/addons/fieldservice_timeline/static/src/js/fsm_gantt.js
odoo/addons/fieldservice_timeline/static/src/js/fsm_gantt_person_filter.js
odoo/addons/fieldservice_timeline/static/src/scss/fsm_gantt_person_filter.scss
odoo/addons/fieldservice_timeline/static/src/xml/fsm_gantt_person_filter.xml
odoo/addons/fieldservice_timeline/tests/__init__.py
odoo/addons/fieldservice_timeline/tests/test_fsm_uninstall.py
odoo/addons/fieldservice_timeline/views/fsm_order.xml
odoo/addons/fieldservice_timeline/views/fsm_team.xml
odoo14_addon_fieldservice_timeline-14.0.1.4.1.dist-info/METADATA
odoo14_addon_fieldservice_timeline-14.0.1.4.1.dist-info/WHEEL
odoo14_addon_fieldservice_timeline-14.0.1.4.1.dist-info/top_level.txt
odoo14_addon_fieldservice_timeline-14.0.1.4.1.dist-info/RECORD
